Workbook

Sheet Sheet1
D2: 1 | E2: 2 | F2: 3 | G2: 4 | H2: 5
C3: PD | D3: 0.01 | E3: 0.02 | F3: 0.03 | G3: 0.04 | H3: 0.05
C4: LGD | D4: 0.4 | E4: 0.4 | F4: 0.4 | G4: 0.4 | H4: 0.4
C6: EIR | D6: 0.1
C8: EAD | D8: 100 | E8: 90 | F8: 80 | G8: 70 | H8: 60
C9: CF | D9: 0 | E9: 10 | F9: 10 | G9: 10 | H9: 70
C11: EL | D11: EAD (no default) minus EAD (with survival given default)

Sheet ContractualCashflows
B3: Notional | D3: 100
B4: Payment Amount | D4: 20
B5: Interest Rate | D5: 0.05
B8: Period t | C8: Interest Payment | D8: Amortization Schedule | E8: Principal Outstanding | F8: Cashflow | G8: Cashflow at Maturity | H8: Interest Rate Yield Curve | I8: Discount Factor | J8: Discounted Cashflow
B9: 0 | C9: 0 | D9: 0 | E9: =D3-D9 -> 100 | F9: 0 | G9: 0 | H9: 0.05 | I9: 1 | J9: =I9*F9 -> 0
B10: 1 | C10: =E9*$D$5 -> 5 | D10: =IF(E9<$D$4,E9,$D$4-C10) -> 15 | E10: =MAX(E9-D10,0) -> 85 | F10: =C10+D10 -> 20 | G10: 0 | H10: 0.05 | I10: =1/(1+H9)^B10 -> 0.95238095 | J10: =I10*F10 -> 19.047619
B11: 2 | C11: =E10*$D$5 -> 4.25 | D11: =IF(E10<$D$4,E10,$D$4-C11) -> 15.75 | E11: =MAX(E10-D11,0) -> 69.25 | F11: =C11+D11 -> 20 | G11: 0 | H11: 0.05 | I11: =1/(1+H10)^B11 -> 0.90702948 | J11: =I11*F11 -> 18.14059
B12: 3 | C12: =E11*$D$5 -> 3.4625 | D12: =IF(E11<$D$4,E11,$D$4-C12) -> 16.5375 | E12: =MAX(E11-D12,0) -> 52.7125 | F12: =C12+D12 -> 20 | G12: 0 | H12: 0.05 | I12: =1/(1+H11)^B12 -> 0.8638376 | J12: =I12*F12 -> 17.276752
B13: 4 | C13: =E12*$D$5 -> 2.635625 | D13: =IF(E12<$D$4,E12,$D$4-C13) -> 17.364375 | E13: =MAX(E12-D13,0) -> 35.348125 | F13: =C13+D13 -> 20 | G13: 0 | H13: 0.05 | I13: =1/(1+H12)^B13 -> 0.82270247 | J13: =I13*F13 -> 16.454049
B14: 5 | C14: =E13*$D$5 -> 1.7674062 | D14: =IF(E13<$D$4,E13,$D$4-C14) -> 18.232594 | E14: =MAX(E13-D14,0) -> 17.115531 | F14: =C14+D14 -> 20 | G14: =E14 -> 17.115531 | H14: 0.05 | I14: =1/(1+H13)^B14 -> 0.78352617 | J14: =I14*F14+G14*I14 -> 29.08099
B15: PV | J15: =SUM(J9:J14) -> 100
B18: Payment amount can be calculated

Sheet Valuation
B2: Probabilities use a mortality rate approach
B3: Put a condition if payment amount is greater than amount outstanding
B4: Effective interest rate does not matter much
H5: Notional | I5: 100
H6: Payment Amount | I6: 20
H7: Interest Rate | I7: 0.06
C8: Key Input | H8: Default Probability (one period) | I8: 0.01
H9: LGD | I9: 0.5
B11: Period t | C11: Default Probabilities | D11: Interval Default Probability | E11: Survival Probability | F11: Interval Survival Probability | G11: Scenaio Probabilities | H11: Interest Payment | I11: Amortization Schedule | J11: Principal Outstanding | K11: Cashflows | L11: Cashflow at Maturity | M11: Interest Rate Yield Curve | N11: Discount Factor | O11: Discounted Contratual Cashflows | P11: Discounted Cashflows Scenarios | Q11: Expected Scenarios
B12: 0 | C12: 0 | D12: =C12 -> 0 | E12: =(1-C12) -> 1 | F12: =1-D12 -> 1 | G12: =D12 -> 0 | H12: 0 | I12: 0 | J12: =I5-I12 -> 100 | K12: 0 | L12: 0 | M12: 0.05 | N12: 1 | O12: =N12*K12 -> 0 | P12: 0
B13: 1 | C13: =I8 -> 0.01 | D13: =(C13-C12) -> 0.01 | E13: =1-C13 -> 0.99 | F13: =1-D13 -> 0.99 | G13: =E12*D13 -> 0.01 | H13: =J12*$I$7 -> 6 | I13: =IF(J12<$I$6,J12,$I$6-H13) -> 14 | J13: =MAX(J12-I13,0) -> 86 | K13: =H13+I13 -> 20 | L13: 0 | M13: 0.05 | N13: =1/(1+M12)^B13 -> 0.95238095 | O13: =N13*K13 -> 19.047619 | P13: =J12*(1-$I$9)*N13 + H13*N13 -> 53.333333 | Q13: Default at 1
B14: 2 | C14: =1-(1-$C$13)^B14 -> 0.0199 | D14: =(C14-C13) -> 0.0099 | E14: =1-C14 -> 0.9801 | F14: =1-D14 -> 0.9901 | G14: =E12*E13*D14 -> 0.009801 | H14: =J13*$I$7 -> 5.16 | I14: =IF(J13<$I$6,J13,$I$6-H14) -> 14.84 | J14: =MAX(J13-I14,0) -> 71.16 | K14: =H14+I14 -> 20 | L14: 0 | M14: 0.05 | N14: =1/(1+M13)^B14 -> 0.90702948 | O14: =N14*K14 -> 18.14059 | P14: =K13*N13+J13*(1-$I$9)*N14+H14*N14 -> 62.730159 | Q14: Default at 2
B15: 3 | C15: =1-(1-$C$13)^B15 -> 0.029701 | D15: =(C15-C14) -> 0.009801 | E15: =1-C15 -> 0.970299 | F15: =1-D15 -> 0.990199 | G15: =F12*F13*F14*D15 -> 0.0096069304 | H15: =J14*$I$7 -> 4.2696 | I15: =IF(J14<$I$6,J14,$I$6-H15) -> 15.7304 | J15: =MAX(J14-I15,0) -> 55.4296 | K15: =H15+I15 -> 20 | L15: 0 | M15: 0.05 | N15: =1/(1+M14)^B15 -> 0.8638376 | O15: =N15*K15 -> 17.276752 | P15: =K13*N13+K14*N14+J14*(1-$I$9)*N15+H15*N15 -> 71.611791 | Q15: Default at 3
B16: 4 | C16: =1-(1-$C$13)^B16 -> 0.03940399 | D16: =(C16-C15) -> 0.00970299 | E16: =1-C16 -> 0.96059601 | F16: =1-D16 -> 0.99029701 | G16: =F12*F13*F14*F15*D16 -> 0.0094176451 | H16: =J15*$I$7 -> 3.325776 | I16: =IF(J15<$I$6,J15,$I$6-H16) -> 16.674224 | J16: =MAX(J15-I16,0) -> 38.755376 | K16: =H16+I16 -> 20 | L16: 0 | M16: 0.05 | N16: =1/(1+M15)^B16 -> 0.82270247 | O16: =N16*K16 -> 16.454049 | P16: =K13*N13+K14*N14+K15*N15+J15*(1-$I$9)*N16+H16*N16 -> 80.002119 | Q16: Default at 4
B17: 5 | C17: =1-(1-$C$13)^B17 -> 0.04900995 | D17: =(C17-C16) -> 0.0096059601 | E17: =1-C17 -> 0.95099005 | F17: =1-D17 -> 0.99039404 | G17: =F12*F13*F14*F15*F16*D17 -> 0.0092330032 | H17: =J16*$I$7 -> 2.3253226 | I17: =IF(J16<$I$6,J16,$I$6-H17) -> 17.674677 | J17: =MAX(J16-I17,0) -> 21.080699 | K17: =H17+I17 -> 20 | L17: =J17 -> 21.080699 | M17: 0.05 | N17: =1/(1+M16)^B17 -> 0.78352617 | O17: =N17*L17+K17*N17 -> 32.187802 | P17: =K13*N13+K14*N14+K15*N15+K16*N16+J16*(1-$I$9)*N17+H17*N17 -> 87.923887 | Q17: Default at 5
B18: 5 | G18: =F13*F14*F15*F16*F17 -> 0.95194142 | M18: 0.05 | P18: =K13*N13+K14*N14+K15*N15+K16*N16+(K17+L17)*N17 -> 103.10681 | Q18: No Default at 5
B19: PV | G19: =SUM(G12:G18) -> 1 | O19: =SUM(O12:O17) -> 103.10681 | P19: =P13*G13+G14*P14+G15*P15+G16*P16+G17*P17+G18*P18 -> 101.553
O21: Expected Loss | P21: =(O19-P19)/I5 -> 0.015538126

Sheet TB ZM3000011467
C3: Notional | D3: 4991005.4
C4: Payment Amount | D4: 768994.56
C5: Interest Rate | D5: 0.15
C6: Default Probability (one period) | D6: 0.00978
C7: LGD | D7: 0.4
C8: Maturity Date | D8: 45684
C9: Issue Date | D9: 45320
C10: Valuation Date | D10: 45657
C11: ISIN | D11: ZM3000011467
C12: Tenor | D12: =DATEDIF(D10,D8,"M") -> 0
C14: EXPECTED AMOUNT APPROACH
C16: Period t | D16: Default Probabilities | E16: Interval Default Probability | F16: Survival Probability | G16: Interval Survival Probability | H16: Scenaio Probabilities | I16: Interest Payment | J16: Amortization Schedule | K16: Principal Outstanding | L16: Cashflows | M16: Cashflow at Maturity | N16: Interest Rate Yield Curve | O16: Discount Factor | P16: Discounted Contratual Cashflows | Q16: Discounted Expected Cashflows
C17: 1 | D17: 0.00978 | E17: =D17 -> 0.00978 | F17: =(1-D17) -> 0.99022 | G17: =1-E17 -> 0.99022 | H17: =D17 -> 0.00978 | I17: =D4 -> 768994.56 | J17: 0 | K17: =D3-J17 -> 4991005.4 | L17: =K17+I17 -> 5760000 | M17: =L17 -> 5760000 | N17: 0.15 | O17: =1/(1+N17)^C17 -> 0.86956522 | P17: =O17*L17 -> 5008695.7 | Q17: =(1-D7)*L17*O17 -> 3005217.4
C18: 1 | H18: =1-H17 -> 0.99022 | I18: =D4 -> 768994.56 | J18: 0 | K18: 4991005.4 | L18: =K18+I18 -> 5760000 | M18: =L18 -> 5760000 | N18: 0.15 | O18: =1/(1+N18)^C18 -> 0.86956522 | P18: 0 | Q18: =L18*O18 -> 5008695.7
C19: PV | H19: =SUM(H17:H18) -> 1 | P19: =SUM(P17:P18) -> 5008695.7 | Q19: =SUMPRODUCT(Q17:Q18,H17:H18) -> 4989101.6
P21: ECL | Q21: =P19-Q19 -> 19594.017
Q22: =Q21/P19 -> 0.003912
C26: LOSS AMOUNT APPROACH
C28: Period t | D28: Default Probabilities | E28: Interval Default Probability | F28: Survival Probability | G28: Interval Survival Probability | H28: Scenaio Probabilities | I28: Interest Payment | J28: Amortization Schedule | K28: Principal Outstanding | L28: Cashflows | M28: Cashflow at Maturity | N28: Interest Rate Yield Curve | O28: Discount Factor | P28: Discounted Contratual Cashflows | Q28: Discounted Loss Given Default
C29: 1 | D29: 0.00978 | E29: =D29 -> 0.00978 | F29: =(1-D29) -> 0.99022 | G29: =1-E29 -> 0.99022 | H29: =D29 -> 0.00978 | I29: =D4 -> 768994.56 | J29: 0 | K29: =D3 -> 4991005.4 | L29: =K29+I29 -> 5760000 | M29: =L29 -> 5760000 | N29: 0.15 | O29: =1/(1+N29)^C29 -> 0.86956522 | P29: =O29*L29 -> 5008695.7 | Q29: =D7*L29*O29 -> 2003478.3
H30: =SUM(H29:H29) -> 0.00978 | P30: ECL | Q30: =SUMPRODUCT(Q29:Q29,H29:H29) -> 19594.017

Sheet TB ZM3000011665
B2: Notional | C2: 4936878.3
B3: Payment Amount | C3: 683455.15
B4: Interest Rate | C4: 0.15
B5: Default Probability (one period) | C5: 0.00978
B6: LGD | C6: 0.4
B7: Maturity Date | C7: 45754
B8: Issue Date | C8: 45390
B9: Valuation Date | C9: 45657
B10: ISIN | C10: ZM3000011665
B11: Tenor | C11: =DATEDIF(C9,C7,"M") -> 3
B15: EXPECTED AMOUNT APPROACH
B17: Period t | C17: Default Probabilities | D17: Interval Default Probability | E17: Survival Probability | F17: Interval Survival Probability | G17: Scenaio Probabilities | H17: Interest Payment | I17: Amortization Schedule | J17: Principal Outstanding | K17: Cashflows | L17: Cashflow at Maturity | M17: Interest Rate Yield Curve | N17: Discount Factor | O17: Discounted Contratual Cashflows | P17: Discounted Expected Cashflows
B18: 1 | C18: 0.00978 | D18: =C18 -> 0.00978 | E18: =(1-C18) -> 0.99022 | F18: =1-D18 -> 0.99022 | G18: =C18 -> 0.00978 | H18: =C3 -> 683455.15 | I18: 0 | J18: =C2 -> 4936878.3 | K18: =J18+H18 -> 5620333.4 | L18: =K18 -> 5620333.4 | M18: =C4 -> 0.15 | N18: =1/(1+M18)^B18 -> 0.86956522 | O18: =N18*K18 -> 4887246.5 | P18: =(1-C6)*K18*N18 -> 2932347.9
B19: 1 | G19: =1-G18 -> 0.99022 | H19: =C3 -> 683455.15 | I19: 0 | J19: =C2 -> 4936878.3 | K19: =J19+H19 -> 5620333.4 | L19: =K19 -> 5620333.4 | M19: =C4 -> 0.15 | N19: =1/(1+M19)^B19 -> 0.86956522 | O19: 0 | P19: =K19*N19 -> 4887246.5
B20: PV | G20: =SUM(G18:G19) -> 1 | O20: =SUM(O18:O19) -> 4887246.5 | P20: =SUMPRODUCT(P18:P19,G18:G19) -> 4868127.6
O22: ECL | P22: =O20-P20 -> 19118.908
B26: LOSS AMOUNT APPROACH
B29: Period t | C29: Default Probabilities | D29: Interval Default Probability | E29: Survival Probability | F29: Interval Survival Probability | G29: Scenaio Probabilities | H29: Interest Payment | I29: Amortization Schedule | J29: Principal Outstanding | K29: Cashflows | L29: Cashflow at Maturity | M29: Interest Rate Yield Curve | N29: Discount Factor | O29: Discounted Contratual Cashflows | P29: Discounted Loss Given Default
B30: 1 | C30: 0.00978 | D30: =C30 -> 0.00978 | E30: =(1-C30) -> 0.99022 | F30: =1-D30 -> 0.99022 | G30: =C30 -> 0.00978 | H30: =C3 -> 683455.15 | I30: 0 | J30: =C2 -> 4936878.3 | K30: =J30+H30 -> 5620333.4 | L30: =K30 -> 5620333.4 | M30: 0.15 | N30: =1/(1+M30)^B30 -> 0.86956522 | O30: =N30*K30 -> 4887246.5 | P30: =C6*K30*N30 -> 1954898.6
G31: =SUM(G30:G30) -> 0.00978 | O31: ECL | P31: =SUMPRODUCT(P30:P30,G30:G30) -> 19118.908

Sheet TB ZM3000011822
C2: Notional | D2: 13022164
C3: Payment Amount | D3: 1541251.6
C4: Interest Rate | D4: 0.15
C5: Default Probability (one period) | D5: 0.00978
C6: LGD | D6: 0.4
C7: Maturity Date | D7: 45810
C8: Issue Date | D8: 45446
C9: Valuation Date | D9: 45657
C10: ISIN | D10: ZM3000011822
C11: Tenor | D11: =DATEDIF(D9,D7,"M") -> 5
C15: EXPECTED AMOUNT APPROACH
C17: Period t | D17: Default Probabilities | E17: Interval Default Probability | F17: Survival Probability | G17: Interval Survival Probability | H17: Scenaio Probabilities | I17: Interest Payment | J17: Amortization Schedule | K17: Principal Outstanding | L17: Cashflows | M17: Cashflow at Maturity | N17: Interest Rate Yield Curve | O17: Discount Factor | P17: Discounted Contratual Cashflows | Q17: Discounted Expected Cashflows
C18: 1 | D18: 0.00978 | E18: =D18 -> 0.00978 | F18: =(1-D18) -> 0.99022 | G18: =1-E18 -> 0.99022 | H18: =D18 -> 0.00978 | I18: =D3 -> 1541251.6 | J18: 0 | K18: =D2 -> 13022164 | L18: =K18+I18 -> 14563416 | M18: =L18 -> 14563416 | N18: =D4 -> 0.15 | O18: =1/(1+N18)^C18 -> 0.86956522 | P18: =O18*L18 -> 12663840 | Q18: =(1-D6)*L18*O18 -> 7598304.1
C19: 1 | H19: =1-H18 -> 0.99022 | I19: =D3 -> 1541251.6 | J19: 0 | K19: =D2 -> 13022164 | L19: =K19+I19 -> 14563416 | M19: =L19 -> 14563416 | N19: =D4 -> 0.15 | O19: =1/(1+N19)^C19 -> 0.86956522 | P19: 0 | Q19: =L19*O19 -> 12663840
C20: PV | H20: =SUM(H18:H19) -> 1 | P20: =SUM(P18:P19) -> 12663840 | Q20: =SUMPRODUCT(Q18:Q19,H18:H19) -> 12614299
P22: ECL | Q22: =P20-Q20 -> 49540.942
C27: LOSS AMOUNT APPROACH
C29: Period t | D29: Default Probabilities | E29: Interval Default Probability | F29: Survival Probability | G29: Interval Survival Probability | H29: Scenaio Probabilities | I29: Interest Payment | J29: Amortization Schedule | K29: Principal Outstanding | L29: Cashflows | M29: Cashflow at Maturity | N29: Interest Rate Yield Curve | O29: Discount Factor | P29: Discounted Contratual Cashflows | Q29: Discounted Loss Given Default
C30: 1 | D30: 0.00978 | E30: =D30 -> 0.00978 | F30: =(1-D30) -> 0.99022 | G30: =1-E30 -> 0.99022 | H30: =D30 -> 0.00978 | I30: =D3 -> 1541251.6 | J30: 0 | K30: =D2 -> 13022164 | L30: =K30+I30 -> 14563416 | M30: =L30 -> 14563416 | N30: =D4 -> 0.15 | O30: =1/(1+N30)^C30 -> 0.86956522 | P30: =O30*L30 -> 12663840 | Q30: =D6*L30*O30 -> 5065536
H31: =SUM(H30:H30) -> 0.00978 | P31: ECL | Q31: =SUMPRODUCT(Q30:Q30,H30:H30) -> 49540.942

Sheet TB ZM3000012101 
C2: Notional | D2: 10929152
C3: Payment Amount | D3: 995600
C4: Interest Rate | D4: 1.15
C5: Default Probability (one period) | D5: 0.00978
C6: LGD | D6: 0.4
C7: Maturity Date | D7: 45905
C8: Issue Date | D8: 45541
C9: Valuation Date | D9: 45657
C10: ISIN | D10: ZM3000012101
C11: Tenor | D11: =DATEDIF(D9,D7,"M") -> 8
C15: EXPECTED AMOUNT APPROACH
C17: Period t | D17: Default Probabilities | E17: Interval Default Probability | F17: Survival Probability | G17: Interval Survival Probability | H17: Scenaio Probabilities | I17: Interest Payment | J17: Amortization Schedule | K17: Principal Outstanding | L17: Cashflows | M17: Cashflow at Maturity | N17: Interest Rate Yield Curve | O17: Discount Factor | P17: Discounted Contratual Cashflows | Q17: Discounted Expected Cashflows
C18: 1 | D18: 0.00978 | E18: =D18 -> 0.00978 | F18: =(1-D18) -> 0.99022 | G18: =1-E18 -> 0.99022 | H18: =D18 -> 0.00978 | I18: =D3 -> 995600 | J18: 0 | K18: =D2 -> 10929152 | L18: =K18+I18 -> 11924752 | M18: =L18 -> 11924752 | N18: =D4 -> 1.15 | O18: =1/(1+N18)^C18 -> 0.46511628 | P18: =O18*L18 -> 5546396.3 | Q18: =(1-D6)*L18*O18 -> 3327837.8
C19: 1 | H19: =1-H18 -> 0.99022 | I19: =D3 -> 995600 | J19: 0 | K19: =D2 -> 10929152 | L19: =K19+I19 -> 11924752 | M19: =L19 -> 11924752 | N19: =D4 -> 1.15 | O19: =1/(1+N19)^C19 -> 0.46511628 | P19: 0 | Q19: =L19*O19 -> 5546396.3
C20: PV | H20: =SUM(H18:H19) -> 1 | P20: =SUM(P18:P19) -> 5546396.3 | Q20: =SUMPRODUCT(Q18:Q19,H18:H19) -> 5524698.8
P22: ECL | Q22: =P20-Q20 -> 21697.502
C27: LOSS AMOUNT APPROACH
C29: Period t | D29: Default Probabilities | E29: Interval Default Probability | F29: Survival Probability | G29: Interval Survival Probability | H29: Scenaio Probabilities | I29: Interest Payment | J29: Amortization Schedule | K29: Principal Outstanding | L29: Cashflows | M29: Cashflow at Maturity | N29: Interest Rate Yield Curve | O29: Discount Factor | P29: Discounted Contratual Cashflows | Q29: Discounted Loss Given Default
C30: 1 | D30: 0.00978 | E30: =D30 -> 0.00978 | F30: =(1-D30) -> 0.99022 | G30: =1-E30 -> 0.99022 | H30: =D30 -> 0.00978 | I30: =D3 -> 995600 | J30: 0 | K30: =D2 -> 10929152 | L30: =K30+I30 -> 11924752 | M30: =L30 -> 11924752 | N30: =D4 -> 1.15 | O30: =1/(1+N30)^C30 -> 0.46511628 | P30: =O30*L30 -> 5546396.3 | Q30: =D6*L30*O30 -> 2218558.5
H31: =SUM(H30:H30) -> 0.00978 | P31: ECL | Q31: =SUMPRODUCT(Q30:Q30,H30:H30) -> 21697.502

Sheet ECL Summary
B4: Scenario Probabilities
B5: Default | C5: 0.0098
B6: Survival | C6: =1-C5 -> 0.9902
B8: Expected Amount Approach
K9: Discounted Expected Cashflows
B10: ISIN | C10: Issue Date | D10: Maturity Date | E10: Notional Amount | F10: Cashflows | G10: Yield | H10: Interest Rate | I10: Discount Factor | J10: Discounted Contratual Cashflows | K10: Default Scenario | L10: Survival Scenario | M10: Total Expected Cashflows | N10: ECL
B11: ZM3000011467 | C11: 45320 | D11: ='TB ZM3000011467'!D8 -> 45684 | E11: ='TB ZM3000011467'!D3 -> 4991005.4 | F11: ='TB ZM3000011467'!L17 -> 5760000 | G11: ='TB ZM3000011467'!D4 -> 768994.56 | H11: ='TB ZM3000011467'!D5 -> 0.15 | I11: =1/(1+H11)^1 -> 0.86956522 | J11: =I11*F11 -> 5008695.7 | K11: ='TB ZM3000011467'!Q17 -> 3005217.4 | L11: ='TB ZM3000011467'!Q18 -> 5008695.7 | M11: ='TB ZM3000011467'!Q19 -> 4989101.6 | N11: ='TB ZM3000011467'!Q21 -> 19594.017
B12: ZM3000011665 | C12: 45390 | D12: ='TB ZM3000011665'!C7 -> 45754 | E12: ='TB ZM3000011665'!C2 -> 4936878.3 | F12: ='TB ZM3000011665'!K18 -> 5620333.4 | G12: ='TB ZM3000011665'!C3 -> 683455.15 | H12: ='TB ZM3000011665'!C4 -> 0.15 | I12: =1/(1+H12)^1 -> 0.86956522 | J12: =I12*F12 -> 4887246.5 | K12: ='TB ZM3000011665'!P18 -> 2932347.9 | L12: ='TB ZM3000011665'!P19 -> 4887246.5 | M12: ='TB ZM3000011665'!P20 -> 4868127.6 | N12: ='TB ZM3000011665'!P22 -> 19118.908
B13: ZM3000011822 | C13: 45446 | D13: ='TB ZM3000011822'!D7 -> 45810 | E13: ='TB ZM3000011822'!D2 -> 13022164 | F13: ='TB ZM3000011822'!L18 -> 14563416 | G13: ='TB ZM3000011822'!D3 -> 1541251.6 | H13: ='TB ZM3000011822'!D4 -> 0.15 | I13: =1/(1+H13)^1 -> 0.86956522 | J13: =I13*F13 -> 12663840 | K13: ='TB ZM3000011822'!Q18 -> 7598304.1 | L13: ='TB ZM3000011822'!Q19 -> 12663840 | M13: ='TB ZM3000011822'!Q20 -> 12614299 | N13: ='TB ZM3000011822'!Q22 -> 49540.942
B14: ZM3000012101 | C14: 45541 | D14: ='TB ZM3000012101 '!D7 -> 45905 | E14: ='TB ZM3000012101 '!D2 -> 10929152 | F14: ='TB ZM3000012101 '!M18 -> 11924752 | G14: ='TB ZM3000012101 '!D3 -> 995600 | H14: ='TB ZM3000012101 '!D4 -> 1.15 | I14: =1/(1+H14)^1 -> 0.46511628 | J14: =I14*F14 -> 5546396.3 | K14: ='TB ZM3000012101 '!Q18 -> 3327837.8 | L14: ='TB ZM3000012101 '!Q19 -> 5546396.3 | M14: ='TB ZM3000012101 '!Q20 -> 5524698.8 | N14: ='TB ZM3000012101 '!Q22 -> 21697.502
B18: Loss Amount Approach
B20: ISIN | C20: Issue Date | D20: Maturity Date | E20: Notional Amount | F20: Cashflows | G20: Yield | H20: Interest Rate | I20: Discount Factor | J20: Discounted Contratual Cashflows | K20: Discounted Loss Given Default | L20: ECL
B21: ZM3000011467 | C21: 45320 | D21: =D11 -> 45684 | E21: =E11 -> 4991005.4 | F21: =F11 -> 5760000 | G21: =G11 -> 768994.56 | H21: =H11 -> 0.15 | I21: =1/(1+H21)^1 -> 0.86956522 | J21: =F21*I21 -> 5008695.7 | K21: ='TB ZM3000011467'!Q29 -> 2003478.3 | L21: ='TB ZM3000011467'!Q30 -> 19594.017
B22: ZM3000011665 | C22: 45390 | D22: =D12 -> 45754 | E22: =E12 -> 4936878.3 | F22: =F12 -> 5620333.4 | G22: =G12 -> 683455.15 | H22: =H12 -> 0.15 | I22: =1/(1+H22)^1 -> 0.86956522 | J22: =F22*I22 -> 4887246.5 | K22: ='TB ZM3000011665'!P30 -> 1954898.6 | L22: ='TB ZM3000011665'!P31 -> 19118.908
B23: ZM3000011822 | C23: 45446 | D23: =D13 -> 45810 | E23: =E13 -> 13022164 | F23: =F13 -> 14563416 | G23: =G13 -> 1541251.6 | H23: =H13 -> 0.15 | I23: =1/(1+H23)^1 -> 0.86956522 | J23: =F23*I23 -> 12663840 | K23: ='TB ZM3000011822'!Q30 -> 5065536 | L23: ='TB ZM3000011822'!Q31 -> 49540.942
B24: ZM3000012101 | C24: 45541 | D24: =D14 -> 45905 | E24: =E14 -> 10929152 | F24: =F14 -> 11924752 | G24: =G14 -> 995600 | H24: =H14 -> 1.15 | I24: =1/(1+H24)^1 -> 0.46511628 | J24: =F24*I24 -> 5546396.3 | K24: ='TB ZM3000012101 '!Q30 -> 2218558.5 | L24: ='TB ZM3000012101 '!Q31 -> 21697.502
